sqldantic/__init__.py
sqldantic/field.py
sqldantic/main.py
sqldantic/orm.py
sqldantic/sqltypes.py
sqldantic/typing_extra.py
sqldantic-0.2.0.dist-info/LICENSE
sqldantic-0.2.0.dist-info/METADATA
sqldantic-0.2.0.dist-info/WHEEL
sqldantic-0.2.0.dist-info/RECORD
