Metadata-Version: 2.1
Name: sqldantic
Version: 0.2.0
Summary: sqlalchemy and pydantic integration.
Home-page: https://github.com/aachurin/sqldantic
License: Unlicense
Author: Andrey Churin
Author-email: aachurin@gmail.com
Requires-Python: >=3.10,<4.0
Classifier: Development Status :: 3 - Alpha
Classifier: Intended Audience :: Developers
Classifier: Intended Audience :: Science/Research
Classifier: Intended Audience :: System Administrators
Classifier: License :: OSI Approved
Classifier: Programming Language :: Python :: 3
Classifier: Programming Language :: Python :: 3.10
Classifier: Programming Language :: Python :: 3.11
Classifier: Programming Language :: Python :: 3.12
Classifier: Programming Language :: Python :: 3 :: Only
Classifier: Topic :: Database
Classifier: Topic :: Database :: Database Engines/Servers
Classifier: Topic :: Internet
Classifier: Topic :: Internet :: WWW/HTTP
Classifier: Topic :: Internet :: WWW/HTTP :: HTTP Servers
Classifier: Typing :: Typed
Requires-Dist: pydantic (>=2.6.3,<3.0.0)
Requires-Dist: sqlalchemy (>=2.0.26,<3.0.0)
Project-URL: Repository, https://github.com/aachurin/sqldantic
